xpress/__init__.py
xpression-0.1.0.dist-info/LICENSE
xpression-0.1.0.dist-info/METADATA
xpression-0.1.0.dist-info/WHEEL
xpression-0.1.0.dist-info/top_level.txt
xpression-0.1.0.dist-info/RECORD
